[{"name": "Agana Heights", "value": "Agana Heights"}, {"name": "Agat", "value": "Agat"}, {"name": "Asan", "value": "Asan"}, {"name": "Barrigada", "value": "Barrigada"}, {"name": "Chalan-Pago-Ordot", "value": "Chalan-Pago-Ordot"}, {"name": "Dededo", "value": "Dededo"}, {"name": "Hagatna", "value": "Hagatna"}, {"name": "Inarajan", "value": "Inarajan"}, {"name": "Mangilao", "value": "Mangilao"}, {"name": "Merizo", "value": "Merizo"}, {"name": "Mongmong-Toto-Maite", "value": "Mongmong-Toto-Maite"}, {"name": "Piti", "value": "Piti"}, {"name": "Santa Rita", "value": "Santa Rita"}, {"name": "Sinajana", "value": "Sinajana"}, {"name": "Talofofo", "value": "Talofofo"}, {"name": "Tamuning", "value": "Tamuning"}, {"name": "Umatac", "value": "Umatac"}, {"name": "Yigo", "value": "Yigo"}, {"name": "Yona", "value": "Yona"}]