[{"name": "`Asir", "value": "`Asir"}, {"name": "Al Bahah", "value": "Al Bahah"}, {"name": "Al Hudud ash Shamaliyah", "value": "Al Hudud ash Shamaliyah"}, {"name": "Al Jawf", "value": "Al Jawf"}, {"name": "Al Madinah", "value": "Al Madinah"}, {"name": "Al Quassim", "value": "Al Quassim"}, {"name": "Ar Riyad", "value": "Ar Riyad"}, {"name": "Ash Sharqiyah", "value": "Ash Sharqiyah"}, {"name": "Ha'il", "value": "Ha'il"}, {"name": "Jizan", "value": "Jizan"}, {"name": "Makkah", "value": "Makkah"}, {"name": "Najran", "value": "Najran"}, {"name": "Tabuk", "value": "Tabuk"}]